ckanmirror/__init__.py
ckanmirror/cli.py
ckanmirror-0.3.0.dist-info/METADATA
ckanmirror-0.3.0.dist-info/WHEEL
ckanmirror-0.3.0.dist-info/entry_points.txt
ckanmirror-0.3.0.dist-info/licenses/AUTHORS.md
ckanmirror-0.3.0.dist-info/licenses/LICENSE.txt
ckanmirror-0.3.0.dist-info/RECORD
