Metadata-Version: 2.4
Name: ckanmirror
Version: 0.3.0
Author-email: Grahame Bowland <grahame@bowland.au>
License-File: AUTHORS.md
License-File: LICENSE.txt
Requires-Python: >=3.11
Requires-Dist: ckanapi
Requires-Dist: humanize
Requires-Dist: requests
Requires-Dist: tqdm
